pds4_utils/__init__.py
pds4_utils/cdf_utils.py
pds4_utils/common.py
pds4_utils/dbase.py
pds4_utils/read.py
pds4_utils/write.py
pds4_utils-0.3.dist-info/LICENSE
pds4_utils-0.3.dist-info/METADATA
pds4_utils-0.3.dist-info/WHEEL
pds4_utils-0.3.dist-info/top_level.txt
pds4_utils-0.3.dist-info/RECORD
