Metadata-Version: 2.1
Name: pds4_utils
Version: 0.3
Summary: A collection of PDS4 utilities
Keywords: PDS,PDS4,archive,data
License-File: LICENSE
Requires-Dist: pandas
Requires-Dist: pyyaml
Requires-Dist: lxml
Requires-Dist: pds4-tools
Requires-Dist: python-version >=3.7
